apdft/__init__.py
apdft/commandline.py
apdft/math.py
apdft/physics.py
apdft/settings.py
apdft/calculator/__init__.py
apdft/calculator/gaussian.py
apdft/calculator/mrcc.py
apdft/calculator/pyscf.py
apdft/calculator/templates/gaussian-run.sh
apdft/calculator/templates/gaussian.txt
apdft/calculator/templates/horton.py
apdft/calculator/templates/mock-run.sh
apdft/calculator/templates/mrcc-run.sh
apdft/calculator/templates/mrcc.txt
apdft/calculator/templates/pyscf-run.sh
apdft/calculator/templates/pyscf.py
apdft-2019.12.2.dist-info/LICENSE
apdft-2019.12.2.dist-info/METADATA
apdft-2019.12.2.dist-info/WHEEL
apdft-2019.12.2.dist-info/entry_points.txt
apdft-2019.12.2.dist-info/top_level.txt
apdft-2019.12.2.dist-info/RECORD
