Metadata-Version: 2.1
Name: apdft
Version: 2019.12.2
Summary: APDFT calculates quantumchemical results for many molecules at once.
Home-page: https://github.com/ferchault/apdft
Author: Guido Falk von Rudorff
Author-email: guido@vonrudorff.de
License: UNKNOWN
Platform: UNKNOWN
Classifier: Development Status :: 3 - Alpha
Classifier: Environment :: Console
Classifier: Intended Audience :: Science/Research
Classifier: License :: OSI Approved :: GNU General Public License v3 (GPLv3)
Classifier: Programming Language :: Python
Requires-Python: >=3.6,<4
Requires-Dist: jinja2
Requires-Dist: basis-set-exchange
Requires-Dist: scipy
Requires-Dist: numpy
Requires-Dist: pandas
Requires-Dist: pyscf
Requires-Dist: structlog
Requires-Dist: colorama
